odoo/addons/delivery_state/README.rst
odoo/addons/delivery_state/__init__.py
odoo/addons/delivery_state/__manifest__.py
odoo/addons/delivery_state/data/ir_cron_data.xml
odoo/addons/delivery_state/data/mail_template.xml
odoo/addons/delivery_state/i18n/delivery_state.pot
odoo/addons/delivery_state/i18n/es.po
odoo/addons/delivery_state/i18n/fr.po
odoo/addons/delivery_state/i18n/it.po
odoo/addons/delivery_state/models/__init__.py
odoo/addons/delivery_state/models/delivery_carrier.py
odoo/addons/delivery_state/models/res_company.py
odoo/addons/delivery_state/models/res_config_settings.py
odoo/addons/delivery_state/models/stock_picking.py
odoo/addons/delivery_state/readme/CONFIGURE.md
odoo/addons/delivery_state/readme/CONTRIBUTORS.md
odoo/addons/delivery_state/readme/DESCRIPTION.md
odoo/addons/delivery_state/readme/USAGE.md
odoo/addons/delivery_state/static/description/icon.png
odoo/addons/delivery_state/static/description/index.html
odoo/addons/delivery_state/tests/__init__.py
odoo/addons/delivery_state/tests/test_delivery_state.py
odoo/addons/delivery_state/views/res_config_settings_view.xml
odoo/addons/delivery_state/views/stock_picking_views.xml
odoo_addon_delivery_state-19.0.1.0.0.2.dist-info/METADATA
odoo_addon_delivery_state-19.0.1.0.0.2.dist-info/WHEEL
odoo_addon_delivery_state-19.0.1.0.0.2.dist-info/top_level.txt
odoo_addon_delivery_state-19.0.1.0.0.2.dist-info/RECORD
